freebox_reboot/__init__.py
freebox_reboot/__main__.py
freebox_reboot/free.cert
freebox_reboot-1.0.1.dist-info/LICENSE
freebox_reboot-1.0.1.dist-info/METADATA
freebox_reboot-1.0.1.dist-info/WHEEL
freebox_reboot-1.0.1.dist-info/entry_points.txt
freebox_reboot-1.0.1.dist-info/top_level.txt
freebox_reboot-1.0.1.dist-info/RECORD
