Metadata-Version: 2.1
Name: freebox-reboot
Version: 1.0.1
Summary: Simple script pour redémarrer une Freebox
Home-page: https://github.com/PabloLec/freebox_reboot
Author: Pablo Lecolinet
Author-email: pablolec@pm.me
License: MIT License
Project-URL: Bug Tracker, https://github.com/PabloLec/freebox_reboot/issues
Keywords: free freebox reboot
Platform: UNKNOWN
Classifier: Programming Language :: Python :: 3.6
Classifier: Programming Language :: Python :: 3.7
Classifier: Programming Language :: Python :: 3.8
Classifier: Programming Language :: Python :: 3.9
Classifier: Programming Language :: Python :: 3.10
Requires-Python: >=3.6
Requires-Dist: certifi (>=2021.5.30)
Requires-Dist: charset-normalizer (>=2.0.3)
Requires-Dist: idna (>=3.2)
Requires-Dist: requests (>=2.26.0)
Requires-Dist: urllib3 (>=1.26.6)
